odoo/addons/procurement_mto_analytic/README.rst
odoo/addons/procurement_mto_analytic/__init__.py
odoo/addons/procurement_mto_analytic/__manifest__.py
odoo/addons/procurement_mto_analytic/i18n/procurement_mto_analytic.pot
odoo/addons/procurement_mto_analytic/i18n/pt.po
odoo/addons/procurement_mto_analytic/i18n/purchase_procurement_analytic.pot
odoo/addons/procurement_mto_analytic/models/__init__.py
odoo/addons/procurement_mto_analytic/models/sale_order_line.py
odoo/addons/procurement_mto_analytic/models/stock_move.py
odoo/addons/procurement_mto_analytic/models/stock_rule.py
odoo/addons/procurement_mto_analytic/readme/CONFIGURE.rst
odoo/addons/procurement_mto_analytic/readme/CONTRIBUTORS.rst
odoo/addons/procurement_mto_analytic/readme/DESCRIPTION.rst
odoo/addons/procurement_mto_analytic/readme/USAGE.rst
odoo/addons/procurement_mto_analytic/static/description/icon.png
odoo/addons/procurement_mto_analytic/static/description/index.html
odoo/addons/procurement_mto_analytic/tests/__init__.py
odoo/addons/procurement_mto_analytic/tests/test_purchase_procurement_analytic.py
odoo12_addon_procurement_mto_analytic-12.0.1.0.0.99.dev8.dist-info/METADATA
odoo12_addon_procurement_mto_analytic-12.0.1.0.0.99.dev8.dist-info/WHEEL
odoo12_addon_procurement_mto_analytic-12.0.1.0.0.99.dev8.dist-info/top_level.txt
odoo12_addon_procurement_mto_analytic-12.0.1.0.0.99.dev8.dist-info/RECORD
